{
  "owners": [
    "6283848833500"
  ],
  "users": {
    "0": {
      "registeredAt": 1770789785245,
      "expiredAt": 1771394585245,
      "type": "trial"
    },
    "4": {
      "registeredAt": 1770992796919,
      "expiredAt": 1771597596919,
      "type": "trial"
    },
    "61": {
      "registeredAt": 1770622328180,
      "expiredAt": 1771227128180,
      "type": "trial"
    },
    "6281331645801": {
      "type": "premium",
      "expiredAt": 1773316037281
    },
    "84336706516": {
      "registeredAt": 1770406364646,
      "expiredAt": 1771011164646,
      "type": "trial"
    },
    "6282262907288": {
      "registeredAt": 1770407134237,
      "expiredAt": 1771011934237,
      "type": "trial"
    },
    "6283172084827": {
      "registeredAt": 1770414858912,
      "expiredAt": 1771019658912,
      "type": "trial"
    },
    "6288279199983": {
      "registeredAt": 1770417080774,
      "expiredAt": 1771021880774,
      "type": "trial"
    },
    "6285777504558": {
      "registeredAt": 1770418710021,
      "expiredAt": 1771023510021,
      "type": "trial"
    },
    "62882019812740": {
      "registeredAt": 1770420101741,
      "expiredAt": 1771024901741,
      "type": "trial"
    },
    "6289677619559": {
      "registeredAt": 1770425656891,
      "expiredAt": 1771030456891,
      "type": "trial"
    },
    "62881036611031": {
      "registeredAt": 1770427784999,
      "expiredAt": 1771032584999,
      "type": "trial"
    },
    "6285849409805": {
      "registeredAt": 1770432369202,
      "expiredAt": 1771037169202,
      "type": "trial"
    },
    "6285719260183": {
      "registeredAt": 1770433967540,
      "expiredAt": 1771038767540,
      "type": "trial"
    },
    "6281939324378": {
      "registeredAt": 1770434115321,
      "expiredAt": 1771038915321,
      "type": "trial"
    },
    "6283161580271": {
      "registeredAt": 1770438262514,
      "expiredAt": 1771043062514,
      "type": "trial"
    },
    "6281235812449": {
      "registeredAt": 1770438547497,
      "expiredAt": 1771043347497,
      "type": "trial"
    },
    "6281376277541": {
      "registeredAt": 1770438992013,
      "expiredAt": 1771043792013,
      "type": "trial"
    },
    "6285823721511": {
      "registeredAt": 1770440986132,
      "expiredAt": 1771045786132,
      "type": "trial"
    },
    "6285351285575": {
      "registeredAt": 1770440997244,
      "expiredAt": 1771045797244,
      "type": "trial"
    },
    "6283198068137": {
      "registeredAt": 1770441336467,
      "expiredAt": 1771046136467,
      "type": "trial"
    },
    "573159157484": {
      "registeredAt": 1770441437712,
      "expiredAt": 1771046237712,
      "type": "trial"
    },
    "62895336876049": {
      "registeredAt": 1770441848434,
      "expiredAt": 1771046648434,
      "type": "trial"
    },
    "6281575579297": {
      "registeredAt": 1770442041833,
      "expiredAt": 1771046841833,
      "type": "trial"
    },
    "6287863117981": {
      "registeredAt": 1770443035164,
      "expiredAt": 1771047835164,
      "type": "trial"
    },
    "584264884816": {
      "registeredAt": 1770443222970,
      "expiredAt": 1771048022970,
      "type": "trial"
    },
    "6281936687711": {
      "registeredAt": 1770446147671,
      "expiredAt": 1771050947671,
      "type": "trial"
    },
    "6283124892736": {
      "registeredAt": 1770446342499,
      "expiredAt": 1771051142499,
      "type": "trial"
    },
    "6289693610733": {
      "registeredAt": 1770447072544,
      "expiredAt": 1771051872544,
      "type": "trial"
    },
    "601135159342": {
      "registeredAt": 1770447219056,
      "expiredAt": 1771052019056,
      "type": "trial"
    },
    "62881010010431": {
      "registeredAt": 1770448699686,
      "expiredAt": 1771053499686,
      "type": "trial"
    },
    "6281237431583": {
      "registeredAt": 1770449182792,
      "expiredAt": 1771053982792,
      "type": "trial"
    },
    "628987649066": {
      "registeredAt": 1770449625399,
      "expiredAt": 1771054425399,
      "type": "trial"
    },
    "6283157364078": {
      "registeredAt": 1770450190898,
      "expiredAt": 1771054990898,
      "type": "trial"
    },
    "6283112471048": {
      "registeredAt": 1770451511337,
      "expiredAt": 1771056311337,
      "type": "trial"
    },
    "6283893377366": {
      "registeredAt": 1770452124134,
      "expiredAt": 1771056924134,
      "type": "trial"
    },
    "629529519793": {
      "registeredAt": 1770455014897,
      "expiredAt": 1771059814897,
      "type": "trial"
    },
    "6289529519793": {
      "registeredAt": 1770455434237,
      "expiredAt": 1771060234237,
      "type": "trial"
    },
    "6283196971240": {
      "registeredAt": 1770456040966,
      "expiredAt": 1771060840966,
      "type": "trial"
    },
    "6283138331063": {
      "registeredAt": 1770457266726,
      "expiredAt": 1771062066726,
      "type": "trial"
    },
    "6282374681505": {
      "registeredAt": 1770457778119,
      "expiredAt": 1771062578119,
      "type": "trial"
    },
    "17828525222": {
      "registeredAt": 1770458246112,
      "expiredAt": 1771063046112,
      "type": "trial"
    },
    "6285746399596": {
      "registeredAt": 1770458580558,
      "expiredAt": 1771063380558,
      "type": "trial"
    },
    "9476426167": {
      "registeredAt": 1770458604994,
      "expiredAt": 1771063404994,
      "type": "trial"
    },
    "6283157705109": {
      "registeredAt": 1770458651302,
      "expiredAt": 1771063451302,
      "type": "trial"
    },
    "94762318338": {
      "registeredAt": 1770459051149,
      "expiredAt": 1771063851149,
      "type": "trial"
    },
    "628984573635": {
      "registeredAt": 1770459316369,
      "expiredAt": 1771064116369,
      "type": "trial"
    },
    "6285385044565": {
      "registeredAt": 1770459427372,
      "expiredAt": 1771064227372,
      "type": "trial"
    },
    "639270632599": {
      "registeredAt": 1770460626743,
      "expiredAt": 1771065426743,
      "type": "trial"
    },
    "6285183467160": {
      "registeredAt": 1770461475967,
      "expiredAt": 1771066275967,
      "type": "trial"
    },
    "6285135955975": {
      "registeredAt": 1770461871166,
      "expiredAt": 1771066671166,
      "type": "trial"
    },
    "62882020841815": {
      "registeredAt": 1770461946411,
      "expiredAt": 1771066746411,
      "type": "trial"
    },
    "62882007655331": {
      "registeredAt": 1770462137607,
      "expiredAt": 1771066937607,
      "type": "trial"
    },
    "6281292969720": {
      "registeredAt": 1770462446225,
      "expiredAt": 1771067246225,
      "type": "trial"
    },
    "6285647518225": {
      "registeredAt": 1770464053483,
      "expiredAt": 1771068853483,
      "type": "trial"
    },
    "6283163028226": {
      "registeredAt": 1770464409846,
      "expiredAt": 1771069209846,
      "type": "trial"
    },
    "6283185054093": {
      "registeredAt": 1770466125880,
      "expiredAt": 1771070925880,
      "type": "trial"
    },
    "6282260218928": {
      "registeredAt": 1770466692948,
      "expiredAt": 1771071492948,
      "type": "trial"
    },
    "584268352633": {
      "registeredAt": 1770467123891,
      "expiredAt": 1771071923891,
      "type": "trial"
    },
    "6285757447387": {
      "registeredAt": 1770467508371,
      "expiredAt": 1771072308371,
      "type": "trial"
    },
    "6285664180268": {
      "registeredAt": 1770467611196,
      "expiredAt": 1771072411196,
      "type": "trial"
    },
    "6282125884283": {
      "registeredAt": 1770467880744,
      "expiredAt": 1771072680744,
      "type": "trial"
    },
    "6285871068603": {
      "registeredAt": 1770468843727,
      "expiredAt": 1771073643727,
      "type": "trial"
    },
    "6282151090398": {
      "registeredAt": 1770469660777,
      "expiredAt": 1771074460777,
      "type": "trial"
    },
    "62895329611764": {
      "registeredAt": 1770470199513,
      "expiredAt": 1771074999513,
      "type": "trial"
    },
    "62882007098238": {
      "registeredAt": 1770470410804,
      "expiredAt": 1771075210804,
      "type": "trial"
    },
    "6289673197452": {
      "registeredAt": 1770470674569,
      "expiredAt": 1771075474569,
      "type": "trial"
    },
    "6285746307210": {
      "registeredAt": 1770470689938,
      "expiredAt": 1771075489938,
      "type": "trial"
    },
    "6287844157490": {
      "registeredAt": 1770471073537,
      "expiredAt": 1771075873537,
      "type": "trial"
    },
    "62881010552571": {
      "registeredAt": 1770471565555,
      "expiredAt": 1771076365555,
      "type": "trial"
    },
    "6287892150321": {
      "registeredAt": 1770472387152,
      "expiredAt": 1771077187152,
      "type": "trial"
    },
    "6283167065336": {
      "registeredAt": 1770472655319,
      "expiredAt": 1771077455319,
      "type": "trial"
    },
    "6283178167808": {
      "registeredAt": 1770473016689,
      "expiredAt": 1771077816689,
      "type": "trial"
    },
    "6285707390310": {
      "registeredAt": 1770475379802,
      "expiredAt": 1771080179802,
      "type": "trial"
    },
    "573159969330": {
      "registeredAt": 1770475863627,
      "expiredAt": 1771080663627,
      "type": "trial"
    },
    "6285155375494": {
      "registeredAt": 1770476702367,
      "expiredAt": 1771081502367,
      "type": "trial"
    },
    "6285894898328": {
      "registeredAt": 1770477892888,
      "expiredAt": 1771082692888,
      "type": "trial"
    },
    "62895320074985": {
      "registeredAt": 1770478415322,
      "expiredAt": 1771083215322,
      "type": "trial"
    },
    "639756982807": {
      "registeredAt": 1770481742999,
      "expiredAt": 1771086542999,
      "type": "trial"
    },
    "6285126234545": {
      "registeredAt": 1770485847456,
      "expiredAt": 1771090647456,
      "type": "trial"
    },
    "62838851335": {
      "registeredAt": 1770486341378,
      "expiredAt": 1771091141378,
      "type": "trial"
    },
    "6282338851335": {
      "registeredAt": 1770486501351,
      "expiredAt": 1771091301351,
      "type": "trial"
    },
    "6285745770379": {
      "registeredAt": 1770487843352,
      "expiredAt": 1771092643352,
      "type": "trial"
    },
    "628123581449": {
      "registeredAt": 1770488271773,
      "expiredAt": 1771093071773,
      "type": "trial"
    },
    "6285730002659": {
      "registeredAt": 1770488975548,
      "expiredAt": 1771093775548,
      "type": "trial"
    },
    "6281912733875": {
      "registeredAt": 1770489632616,
      "expiredAt": 1771094432616,
      "type": "trial"
    },
    "6289502046196": {
      "registeredAt": 1770490398962,
      "expiredAt": 1771095198962,
      "type": "trial"
    },
    "50935866921": {
      "registeredAt": 1770491175129,
      "expiredAt": 1771095975129,
      "type": "trial"
    },
    "50935867376": {
      "registeredAt": 1770492678452,
      "expiredAt": 1771097478452,
      "type": "trial"
    },
    "628216902564": {
      "registeredAt": 1770493961155,
      "expiredAt": 1771098761155,
      "type": "trial"
    },
    "6283125515327": {
      "registeredAt": 1770497002882,
      "expiredAt": 1771101802882,
      "type": "trial"
    },
    "6285396864549": {
      "registeredAt": 1770505159047,
      "expiredAt": 1771109959047,
      "type": "trial"
    },
    "6282298274996": {
      "registeredAt": 1770507950539,
      "expiredAt": 1771112750539,
      "type": "trial"
    },
    "6282230186292": {
      "registeredAt": 1770508850552,
      "expiredAt": 1771113650552,
      "type": "trial"
    },
    "249110795517": {
      "registeredAt": 1770509986194,
      "expiredAt": 1771114786194,
      "type": "trial"
    },
    "6285774003436": {
      "registeredAt": 1770511278727,
      "expiredAt": 1771116078727,
      "type": "trial"
    },
    "6283187255547": {
      "registeredAt": 1770514133959,
      "expiredAt": 1771118933959,
      "type": "trial"
    },
    "6283128412936": {
      "registeredAt": 1770515568475,
      "expiredAt": 1771120368475,
      "type": "trial"
    },
    "6285726657104": {
      "registeredAt": 1770515888194,
      "expiredAt": 1771120688194,
      "type": "trial"
    },
    "6283110993128": {
      "registeredAt": 1770517359337,
      "expiredAt": 1771122159337,
      "type": "trial"
    },
    "628985004529": {
      "registeredAt": 1770518422437,
      "expiredAt": 1771123222437,
      "type": "trial"
    },
    "628133077562": {
      "registeredAt": 1770518712549,
      "expiredAt": 1771123512549,
      "type": "trial"
    },
    "6285179799727": {
      "registeredAt": 1770519057219,
      "expiredAt": 1771123857219,
      "type": "trial"
    },
    "6285697651400": {
      "registeredAt": 1770519514626,
      "expiredAt": 1771124314626,
      "type": "trial"
    },
    "6285787991049": {
      "registeredAt": 1770519573822,
      "expiredAt": 1771124373822,
      "type": "trial"
    },
    "6285814968350": {
      "registeredAt": 1770519636011,
      "expiredAt": 1771124436011,
      "type": "trial"
    },
    "6285374968366": {
      "registeredAt": 1770520880707,
      "expiredAt": 1771125680707,
      "type": "trial"
    },
    "6285373968366": {
      "registeredAt": 1770521011105,
      "expiredAt": 1771125811105,
      "type": "trial"
    },
    "6287891564050": {
      "registeredAt": 1770522180888,
      "expiredAt": 1771126980888,
      "type": "trial"
    },
    "601167215583": {
      "registeredAt": 1770523876224,
      "expiredAt": 1771128676224,
      "type": "trial"
    },
    "27782367055": {
      "registeredAt": 1770523993942,
      "expiredAt": 1771128793942,
      "type": "trial"
    },
    "6285727089972": {
      "registeredAt": 1770524880112,
      "expiredAt": 1771129680112,
      "type": "trial"
    },
    "6287874262304": {
      "registeredAt": 1770525878081,
      "expiredAt": 1771130678081,
      "type": "trial"
    },
    "60169543596": {
      "registeredAt": 1770526509383,
      "expiredAt": 1771131309383,
      "type": "trial"
    },
    "94768293498": {
      "registeredAt": 1770527828994,
      "expiredAt": 1771132628994,
      "type": "trial"
    },
    "584166211703": {
      "registeredAt": 1770528883120,
      "expiredAt": 1771133683120,
      "type": "trial"
    },
    "6285113044711": {
      "registeredAt": 1770529400335,
      "expiredAt": 1771134200335,
      "type": "trial"
    },
    "639525566481": {
      "registeredAt": 1770529415792,
      "expiredAt": 1771134215792,
      "type": "trial"
    },
    "6285124530381": {
      "registeredAt": 1770529948336,
      "expiredAt": 1771134748336,
      "type": "trial"
    },
    "62881027544791": {
      "registeredAt": 1770530059838,
      "expiredAt": 1771134859838,
      "type": "trial"
    },
    "919134780354": {
      "registeredAt": 1770530925229,
      "expiredAt": 1771135725229,
      "type": "trial"
    },
    "627891564036": {
      "registeredAt": 1770531226027,
      "expiredAt": 1771136026027,
      "type": "trial"
    },
    "6287891564036": {
      "registeredAt": 1770531555778,
      "expiredAt": 1771136355778,
      "type": "trial"
    },
    "639269620664": {
      "registeredAt": 1770533650962,
      "expiredAt": 1771138450962,
      "type": "trial"
    },
    "6282180262243": {
      "registeredAt": 1770533751363,
      "expiredAt": 1771138551363,
      "type": "trial"
    },
    "6285134054093": {
      "registeredAt": 1770535822292,
      "expiredAt": 1771140622292,
      "type": "trial"
    },
    "628386875446": {
      "registeredAt": 1770536962552,
      "expiredAt": 1771141762552,
      "type": "trial"
    },
    "84939321253": {
      "registeredAt": 1770538399312,
      "expiredAt": 1771143199312,
      "type": "trial"
    },
    "6289502658933": {
      "registeredAt": 1770538441074,
      "expiredAt": 1771143241074,
      "type": "trial"
    },
    "639260296682": {
      "registeredAt": 1770540403484,
      "expiredAt": 1771145203484,
      "type": "trial"
    },
    "6288994218646": {
      "registeredAt": 1770540759181,
      "expiredAt": 1771145559181,
      "type": "trial"
    },
    "6285624205395": {
      "registeredAt": 1770541239278,
      "expiredAt": 1771146039278,
      "type": "trial"
    },
    "6289529224938": {
      "registeredAt": 1770541262007,
      "expiredAt": 1771146062007,
      "type": "trial"
    },
    "6289529211724": {
      "registeredAt": 1770541352018,
      "expiredAt": 1771146152018,
      "type": "trial"
    },
    "6289528269430": {
      "registeredAt": 1770541654558,
      "expiredAt": 1771146454558,
      "type": "trial"
    },
    "6285381650320": {
      "registeredAt": 1770542868962,
      "expiredAt": 1771147668962,
      "type": "trial"
    },
    "6285863292846": {
      "registeredAt": 1770543525797,
      "expiredAt": 1771148325797,
      "type": "trial"
    },
    "6282211828718": {
      "registeredAt": 1770543796988,
      "expiredAt": 1771148596988,
      "type": "trial"
    },
    "6285362073387": {
      "registeredAt": 1770543857303,
      "expiredAt": 1771148657303,
      "type": "trial"
    },
    "6285735624297": {
      "registeredAt": 1770548191049,
      "expiredAt": 1771152991049,
      "type": "trial"
    },
    "6282263907288": {
      "registeredAt": 1770548261853,
      "expiredAt": 1771153061853,
      "type": "trial"
    },
    "62895392113829": {
      "registeredAt": 1770548728310,
      "expiredAt": 1771153528310,
      "type": "trial"
    },
    "62895393517727": {
      "registeredAt": 1770550082365,
      "expiredAt": 1771154882365,
      "type": "trial"
    },
    "62895381012776": {
      "registeredAt": 1770550309632,
      "expiredAt": 1771155109632,
      "type": "trial"
    },
    "6281568251048": {
      "registeredAt": 1770552894381,
      "expiredAt": 1771157694381,
      "type": "trial"
    },
    "3197010504226": {
      "registeredAt": 1770553047164,
      "expiredAt": 1771157847164,
      "type": "trial"
    },
    "6285798408015": {
      "registeredAt": 1770553705814,
      "expiredAt": 1771158505814,
      "type": "trial"
    },
    "6285711059512": {
      "registeredAt": 1770554053984,
      "expiredAt": 1771158853984,
      "type": "trial"
    },
    "59177537918": {
      "registeredAt": 1770554362699,
      "expiredAt": 1771159162699,
      "type": "trial"
    },
    "6285177168391": {
      "registeredAt": 1770554786519,
      "expiredAt": 1771159586519,
      "type": "trial"
    },
    "6283181421387": {
      "registeredAt": 1770556802548,
      "expiredAt": 1771161602548,
      "type": "trial"
    },
    "254114281354": {
      "registeredAt": 1770557139320,
      "expiredAt": 1771161939320,
      "type": "trial"
    },
    "62881038242537": {
      "registeredAt": 1770557380819,
      "expiredAt": 1771162180819,
      "type": "trial"
    },
    "6285141569818": {
      "registeredAt": 1770559542994,
      "expiredAt": 1771164342994,
      "type": "trial"
    },
    "6285827657167": {
      "registeredAt": 1770559879187,
      "expiredAt": 1771164679187,
      "type": "trial"
    },
    "6289508846808": {
      "registeredAt": 1770560135053,
      "expiredAt": 1771164935053,
      "type": "trial"
    },
    "6285729659732": {
      "registeredAt": 1770560429899,
      "expiredAt": 1771165229899,
      "type": "trial"
    },
    "6285178485434": {
      "registeredAt": 1770560928926,
      "expiredAt": 1771165728926,
      "type": "trial"
    },
    "6288242935717": {
      "registeredAt": 1770561365920,
      "expiredAt": 1771166165920,
      "type": "trial"
    },
    "6285641110806": {
      "registeredAt": 1770562309518,
      "expiredAt": 1771167109518,
      "type": "trial"
    },
    "6287810342030": {
      "registeredAt": 1770562340480,
      "expiredAt": 1771167140480,
      "type": "trial"
    },
    "6283837156574": {
      "registeredAt": 1770562542408,
      "expiredAt": 1771167342408,
      "type": "trial"
    },
    "916290842935": {
      "registeredAt": 1770563154092,
      "expiredAt": 1771167954092,
      "type": "trial"
    },
    "6283164807556": {
      "registeredAt": 1770563447359,
      "expiredAt": 1771168247359,
      "type": "trial"
    },
    "6283115029374": {
      "registeredAt": 1770563853564,
      "expiredAt": 1771168653564,
      "type": "trial"
    },
    "6283157382870": {
      "registeredAt": 1770564327858,
      "expiredAt": 1771169127858,
      "type": "trial"
    },
    "6282313169527": {
      "registeredAt": 1770564554839,
      "expiredAt": 1771169354839,
      "type": "trial"
    },
    "6287888472791": {
      "registeredAt": 1770564746079,
      "expiredAt": 1771169546079,
      "type": "trial"
    },
    "6285715909640": {
      "registeredAt": 1770564865437,
      "expiredAt": 1771169665437,
      "type": "trial"
    },
    "623857289954": {
      "registeredAt": 1770565525510,
      "expiredAt": 1771170325510,
      "type": "trial"
    },
    "6283857289954": {
      "registeredAt": 1770565666504,
      "expiredAt": 1771170466504,
      "type": "trial"
    },
    "6283842987854": {
      "registeredAt": 1770566123218,
      "expiredAt": 1771170923218,
      "type": "trial"
    },
    "6285804173994": {
      "registeredAt": 1770566219877,
      "expiredAt": 1771171019877,
      "type": "trial"
    },
    "6289656097060": {
      "registeredAt": 1770567651571,
      "expiredAt": 1771172451571,
      "type": "trial"
    },
    "6285184519716": {
      "registeredAt": 1770568416411,
      "expiredAt": 1771173216411,
      "type": "trial"
    },
    "639976737868": {
      "registeredAt": 1770568504247,
      "expiredAt": 1771173304247,
      "type": "trial"
    },
    "6285143835085": {
      "registeredAt": 1770568954680,
      "expiredAt": 1771173754680,
      "type": "trial"
    },
    "6383157251361": {
      "registeredAt": 1770569158919,
      "expiredAt": 1771173958919,
      "type": "trial"
    },
    "6285606632344": {
      "registeredAt": 1770569413073,
      "expiredAt": 1771174213073,
      "type": "trial"
    },
    "918609918485": {
      "registeredAt": 1770575067035,
      "expiredAt": 1771179867035,
      "type": "trial"
    },
    "6282291046967": {
      "registeredAt": 1770576605944,
      "expiredAt": 1771181405944,
      "type": "trial"
    },
    "6285353233967": {
      "registeredAt": 1770576730929,
      "expiredAt": 1771181530929,
      "type": "trial"
    },
    "6288994423644": {
      "registeredAt": 1770577500053,
      "expiredAt": 1771182300053,
      "type": "trial"
    },
    "6285134362253": {
      "registeredAt": 1770586934300,
      "expiredAt": 1771191734300,
      "type": "trial"
    },
    "6288983615975": {
      "registeredAt": 1770588081969,
      "expiredAt": 1771192881969,
      "type": "trial"
    },
    "62857765209460": {
      "registeredAt": 1770589326982,
      "expiredAt": 1771194126982,
      "type": "trial"
    },
    "6285801080654": {
      "registeredAt": 1770589953356,
      "expiredAt": 1771194753356,
      "type": "trial"
    },
    "62858286571687": {
      "registeredAt": 1770590836275,
      "expiredAt": 1771195636275,
      "type": "trial"
    },
    "6282315017793": {
      "registeredAt": 1770592498728,
      "expiredAt": 1771197298728,
      "type": "trial"
    },
    "639759808992": {
      "registeredAt": 1770592707122,
      "expiredAt": 1771197507122,
      "type": "trial"
    },
    "6289526446043": {
      "registeredAt": 1770600193497,
      "expiredAt": 1771204993497,
      "type": "trial"
    },
    "6285888245246": {
      "registeredAt": 1770602713836,
      "expiredAt": 1771207513836,
      "type": "trial"
    },
    "6289524119443": {
      "registeredAt": 1770604661959,
      "expiredAt": 1771209461959,
      "type": "trial"
    },
    "6283169518597": {
      "registeredAt": 1770605518773,
      "expiredAt": 1771210318773,
      "type": "trial"
    },
    "6287746297013": {
      "registeredAt": 1770606252727,
      "expiredAt": 1771211052727,
      "type": "trial"
    },
    "628388027823": {
      "registeredAt": 1770607515004,
      "expiredAt": 1771212315004,
      "type": "trial"
    },
    "6281326329126": {
      "registeredAt": 1770609732571,
      "expiredAt": 1771214532571,
      "type": "trial"
    },
    "6285942503512": {
      "registeredAt": 1770610615005,
      "expiredAt": 1771215415005,
      "type": "trial"
    },
    "6283175431053": {
      "registeredAt": 1770611106885,
      "expiredAt": 1771215906885,
      "type": "trial"
    },
    "6285810441694": {
      "registeredAt": 1770612317377,
      "expiredAt": 1771217117377,
      "type": "trial"
    },
    "639616128224": {
      "registeredAt": 1770614522874,
      "expiredAt": 1771219322874,
      "type": "trial"
    },
    "6283148114477": {
      "registeredAt": 1770616936172,
      "expiredAt": 1771221736172,
      "type": "trial"
    },
    "6283183857519": {
      "registeredAt": 1770618834543,
      "expiredAt": 1771223634543,
      "type": "trial"
    },
    "6283182846453": {
      "registeredAt": 1770619191652,
      "expiredAt": 1771223991652,
      "type": "trial"
    },
    "62895324906156": {
      "registeredAt": 1770620468041,
      "expiredAt": 1771225268041,
      "type": "trial"
    },
    "6288221858038": {
      "registeredAt": 1770620808302,
      "expiredAt": 1771225608302,
      "type": "trial"
    },
    "628131659934": {
      "registeredAt": 1770621109247,
      "expiredAt": 1771225909247,
      "type": "trial"
    },
    "62895384151774": {
      "registeredAt": 1770621815894,
      "expiredAt": 1771226615894,
      "type": "trial"
    },
    "6881082777773": {
      "registeredAt": 1770622277100,
      "expiredAt": 1771227077100,
      "type": "trial"
    },
    "6285720630382": {
      "registeredAt": 1770622346789,
      "expiredAt": 1771227146789,
      "type": "trial"
    },
    "62881082777773": {
      "registeredAt": 1770622364452,
      "expiredAt": 1771227164452,
      "type": "trial"
    },
    "6287813661902": {
      "registeredAt": 1770622746337,
      "expiredAt": 1771227546337,
      "type": "trial"
    },
    "62087813661902": {
      "registeredAt": 1770623035421,
      "expiredAt": 1771227835421,
      "type": "trial"
    },
    "6285168166071": {
      "registeredAt": 1770623139594,
      "expiredAt": 1771227939594,
      "type": "trial"
    },
    "6288245258871": {
      "registeredAt": 1770623549962,
      "expiredAt": 1771228349962,
      "type": "trial"
    },
    "6285143739345": {
      "registeredAt": 1770624561214,
      "expiredAt": 1771229361214,
      "type": "trial"
    },
    "6283830186498": {
      "registeredAt": 1770624766139,
      "expiredAt": 1771229566139,
      "type": "trial"
    },
    "62882005963367": {
      "registeredAt": 1770625176654,
      "expiredAt": 1771229976654,
      "type": "trial"
    },
    "601123103738": {
      "registeredAt": 1770626614751,
      "expiredAt": 1771231414751,
      "type": "trial"
    },
    "639709439288": {
      "registeredAt": 1770626764633,
      "expiredAt": 1771231564633,
      "type": "trial"
    },
    "628984504968": {
      "registeredAt": 1770627280074,
      "expiredAt": 1771232080074,
      "type": "trial"
    },
    "639602587760": {
      "registeredAt": 1770627559315,
      "expiredAt": 1771232359315,
      "type": "trial"
    },
    "6285720466787": {
      "registeredAt": 1770628298300,
      "expiredAt": 1771233098300,
      "type": "trial"
    },
    "6281373221926": {
      "registeredAt": 1770628305001,
      "expiredAt": 1771233105001,
      "type": "trial"
    },
    "6283844281141": {
      "registeredAt": 1770628813302,
      "expiredAt": 1771233613302,
      "type": "trial"
    },
    "085150857940": {
      "registeredAt": 1770630444872,
      "expiredAt": 1771235244872,
      "type": "trial"
    },
    "85150857940": {
      "registeredAt": 1770630615744,
      "expiredAt": 1771235415744,
      "type": "trial"
    },
    "584263822504": {
      "registeredAt": 1770630990270,
      "expiredAt": 1771235790270,
      "type": "trial"
    },
    "628164385136": {
      "registeredAt": 1770631088900,
      "expiredAt": 1771235888900,
      "type": "trial"
    },
    "6285702655660": {
      "registeredAt": 1770631248769,
      "expiredAt": 1771236048769,
      "type": "trial"
    },
    "6289528504763": {
      "registeredAt": 1770631294807,
      "expiredAt": 1771236094807,
      "type": "trial"
    },
    "6285194355880": {
      "registeredAt": 1770631716182,
      "expiredAt": 1771236516182,
      "type": "trial"
    },
    "62882008720033": {
      "registeredAt": 1770631875399,
      "expiredAt": 1771236675399,
      "type": "trial"
    },
    "6285770680277": {
      "registeredAt": 1770632031152,
      "expiredAt": 1771236831152,
      "type": "trial"
    },
    "584164106597": {
      "registeredAt": 1770632401111,
      "expiredAt": 1771237201111,
      "type": "trial"
    },
    "639260215149": {
      "registeredAt": 1770632403595,
      "expiredAt": 1771237203595,
      "type": "trial"
    },
    "6288277315521": {
      "registeredAt": 1770632431964,
      "expiredAt": 1771237231964,
      "type": "trial"
    },
    "6283147284937": {
      "registeredAt": 1770632714049,
      "expiredAt": 1771237514049,
      "type": "trial"
    },
    "6283111684823": {
      "registeredAt": 1770632939389,
      "expiredAt": 1771237739389,
      "type": "trial"
    },
    "62895412815023": {
      "registeredAt": 1770634328454,
      "expiredAt": 1771239128454,
      "type": "trial"
    },
    "57721755025": {
      "registeredAt": 1770634730711,
      "expiredAt": 1771239530711,
      "type": "trial"
    },
    "6283847423918": {
      "registeredAt": 1770634825632,
      "expiredAt": 1771239625632,
      "type": "trial"
    },
    "254721755025": {
      "registeredAt": 1770634946263,
      "expiredAt": 1771239746263,
      "type": "trial"
    },
    "6282110764762": {
      "registeredAt": 1770635139124,
      "expiredAt": 1771239939124,
      "type": "trial"
    },
    "6285168609742": {
      "registeredAt": 1770635353468,
      "expiredAt": 1771240153468,
      "type": "trial"
    },
    "6288267045819": {
      "registeredAt": 1770635433723,
      "expiredAt": 1771240233723,
      "type": "trial"
    },
    "6283873821272": {
      "registeredAt": 1770635668397,
      "expiredAt": 1771240468397,
      "type": "trial"
    },
    "628973672495": {
      "registeredAt": 1770636499092,
      "expiredAt": 1771241299092,
      "type": "trial"
    },
    "628973237942": {
      "registeredAt": 1770638657679,
      "expiredAt": 1771243457679,
      "type": "trial"
    },
    "6285124737044": {
      "registeredAt": 1770639409482,
      "expiredAt": 1771244209482,
      "type": "trial"
    },
    "6281938243293": {
      "registeredAt": 1770639595078,
      "expiredAt": 1771244395078,
      "type": "trial"
    },
    "628972100436": {
      "registeredAt": 1770639707557,
      "expiredAt": 1771244507557,
      "type": "trial"
    },
    "6285810551694": {
      "registeredAt": 1770640323504,
      "expiredAt": 1771245123504,
      "type": "trial"
    },
    "51992707877": {
      "registeredAt": 1770641084591,
      "expiredAt": 1771245884591,
      "type": "trial"
    },
    "6283167225165": {
      "registeredAt": 1770641445869,
      "expiredAt": 1771246245869,
      "type": "trial"
    },
    "6385148040107": {
      "registeredAt": 1770642133612,
      "expiredAt": 1771246933612,
      "type": "trial"
    },
    "6285148040107": {
      "registeredAt": 1770642155846,
      "expiredAt": 1771246955846,
      "type": "trial"
    },
    "919382180863": {
      "registeredAt": 1770643090673,
      "expiredAt": 1771247890673,
      "type": "trial"
    },
    "6288245655373": {
      "registeredAt": 1770644141861,
      "expiredAt": 1771248941861,
      "type": "trial"
    },
    "6282121554016": {
      "registeredAt": 1770644452021,
      "expiredAt": 1771249252021,
      "type": "trial"
    },
    "6285647743662": {
      "registeredAt": 1770644599790,
      "expiredAt": 1771249399790,
      "type": "trial"
    },
    "6285864940538": {
      "registeredAt": 1770644619336,
      "expiredAt": 1771249419336,
      "type": "trial"
    },
    "6282170506973": {
      "registeredAt": 1770644703167,
      "expiredAt": 1771249503167,
      "type": "trial"
    },
    "6287897494907": {
      "registeredAt": 1770645073285,
      "expiredAt": 1771249873285,
      "type": "trial"
    },
    "6285247169763": {
      "registeredAt": 1770645334059,
      "expiredAt": 1771250134059,
      "type": "trial"
    },
    "6283178649119": {
      "registeredAt": 1770645577950,
      "expiredAt": 1771250377950,
      "type": "trial"
    },
    "6281239683614": {
      "registeredAt": 1770645653990,
      "expiredAt": 1771250453990,
      "type": "trial"
    },
    "6283137493581": {
      "registeredAt": 1770647706761,
      "expiredAt": 1771252506761,
      "type": "trial"
    },
    "6285124737183": {
      "registeredAt": 1770647716880,
      "expiredAt": 1771252516880,
      "type": "trial"
    },
    "584261971456": {
      "registeredAt": 1770649854090,
      "expiredAt": 1771254654090,
      "type": "trial"
    },
    "6283898241085": {
      "registeredAt": 1770651029365,
      "expiredAt": 1771255829365,
      "type": "trial"
    },
    "62895391037361": {
      "registeredAt": 1770651056296,
      "expiredAt": 1771255856296,
      "type": "trial"
    },
    "6283172559293": {
      "registeredAt": 1770651191208,
      "expiredAt": 1771255991208,
      "type": "trial"
    },
    "6282297898977": {
      "registeredAt": 1770654012896,
      "expiredAt": 1771258812896,
      "type": "trial"
    },
    "639382519597": {
      "registeredAt": 1770655188344,
      "expiredAt": 1771259988344,
      "type": "trial"
    },
    "6288988307539": {
      "registeredAt": 1770655695827,
      "expiredAt": 1771260495827,
      "type": "trial"
    },
    "628811342500": {
      "registeredAt": 1770656170905,
      "expiredAt": 1771260970905,
      "type": "trial"
    },
    "6283896563492": {
      "registeredAt": 1770656396800,
      "expiredAt": 1771261196800,
      "type": "trial"
    },
    "6285135329241": {
      "registeredAt": 1770658840048,
      "expiredAt": 1771263640048,
      "type": "trial"
    },
    "6289660102960": {
      "registeredAt": 1770660327232,
      "expiredAt": 1771265127232,
      "type": "trial"
    },
    "6282170774088": {
      "registeredAt": 1770661616387,
      "expiredAt": 1771266416387,
      "type": "trial"
    },
    "6287855634096": {
      "registeredAt": 1770661739988,
      "expiredAt": 1771266539988,
      "type": "trial"
    },
    "955599003431": {
      "registeredAt": 1770664875031,
      "expiredAt": 1771269675031,
      "type": "trial"
    },
    "995599003431": {
      "registeredAt": 1770665000628,
      "expiredAt": 1771269800628,
      "type": "trial"
    },
    "6285135305064": {
      "registeredAt": 1770677688969,
      "expiredAt": 1771282488969,
      "type": "trial"
    },
    "584167503512": {
      "registeredAt": 1770678380466,
      "expiredAt": 1771283180466,
      "type": "trial"
    },
    "6282381160398": {
      "registeredAt": 1770678910735,
      "expiredAt": 1771283710735,
      "type": "trial"
    },
    "6287879287332": {
      "registeredAt": 1770680402825,
      "expiredAt": 1771285202825,
      "type": "trial"
    },
    "6487879287332": {
      "registeredAt": 1770680745111,
      "expiredAt": 1771285545111,
      "type": "trial"
    },
    "6281233162058": {
      "registeredAt": 1770684389790,
      "expiredAt": 1771289189790,
      "type": "trial"
    },
    "621833162058": {
      "registeredAt": 1770685184337,
      "expiredAt": 1771289984337,
      "type": "trial"
    },
    "6283125822118": {
      "registeredAt": 1770685540860,
      "expiredAt": 1771290340860,
      "type": "trial"
    },
    "6282379622599": {
      "registeredAt": 1770685748287,
      "expiredAt": 1771290548287,
      "type": "trial"
    },
    "6289518030754": {
      "registeredAt": 1770686249604,
      "expiredAt": 1771291049604,
      "type": "trial"
    },
    "6283179374057": {
      "registeredAt": 1770687030316,
      "expiredAt": 1771291830316,
      "type": "trial"
    },
    "6288987046342": {
      "registeredAt": 1770688510185,
      "expiredAt": 1771293310185,
      "type": "trial"
    },
    "6283844527611": {
      "registeredAt": 1770693012311,
      "expiredAt": 1771297812311,
      "type": "trial"
    },
    "6285815243597": {
      "registeredAt": 1770693251629,
      "expiredAt": 1771298051629,
      "type": "trial"
    },
    "6288291852600": {
      "registeredAt": 1770693402711,
      "expiredAt": 1771298202711,
      "type": "trial"
    },
    "6285959025242": {
      "registeredAt": 1770693496818,
      "expiredAt": 1771298296818,
      "type": "trial"
    },
    "6283180225368": {
      "registeredAt": 1770693669643,
      "expiredAt": 1771298469643,
      "type": "trial"
    },
    "6285973027990": {
      "registeredAt": 1770696037187,
      "expiredAt": 1771300837187,
      "type": "trial"
    },
    "6282179377911": {
      "registeredAt": 1770696104608,
      "expiredAt": 1771300904608,
      "type": "trial"
    },
    "6283167052011": {
      "registeredAt": 1770696793705,
      "expiredAt": 1771301593705,
      "type": "trial"
    },
    "62856285168957611": {
      "registeredAt": 1770697651537,
      "expiredAt": 1771302451537,
      "type": "trial"
    },
    "6285268957611": {
      "registeredAt": 1770697712015,
      "expiredAt": 1771302512015,
      "type": "trial"
    },
    "6285283380274": {
      "registeredAt": 1770697765153,
      "expiredAt": 1771302565153,
      "type": "trial"
    },
    "6281248693922": {
      "registeredAt": 1770702653658,
      "expiredAt": 1771307453658,
      "type": "trial"
    },
    "6285168957611": {
      "registeredAt": 1770703651056,
      "expiredAt": 1771308451056,
      "type": "trial"
    },
    "6283861162142": {
      "registeredAt": 1770703967705,
      "expiredAt": 1771308767705,
      "type": "trial"
    },
    "6287881865022": {
      "registeredAt": 1770705825581,
      "expiredAt": 1771310625581,
      "type": "trial"
    },
    "62895622315235": {
      "registeredAt": 1770706566327,
      "expiredAt": 1771311366327,
      "type": "trial"
    },
    "62386896792": {
      "registeredAt": 1770706953570,
      "expiredAt": 1771311753570,
      "type": "trial"
    },
    "6289672925052": {
      "registeredAt": 1770709142201,
      "expiredAt": 1771313942201,
      "type": "trial"
    },
    "6288707099859": {
      "registeredAt": 1770709698333,
      "expiredAt": 1771314498333,
      "type": "trial"
    },
    "6283120992639": {
      "registeredAt": 1770709791395,
      "expiredAt": 1771314591395,
      "type": "trial"
    },
    "6285218854817": {
      "registeredAt": 1770710936998,
      "expiredAt": 1771315736998,
      "type": "trial"
    },
    "6283113268204": {
      "registeredAt": 1770711322939,
      "expiredAt": 1771316122939,
      "type": "trial"
    },
    "6282218274442": {
      "registeredAt": 1770712582699,
      "expiredAt": 1771317382699,
      "type": "trial"
    },
    "923557020722": {
      "registeredAt": 1770713508474,
      "expiredAt": 1771318308474,
      "type": "trial"
    },
    "628976953512": {
      "registeredAt": 1770713930225,
      "expiredAt": 1771318730225,
      "type": "trial"
    },
    "6283193419314": {
      "registeredAt": 1770714540973,
      "expiredAt": 1771319340973,
      "type": "trial"
    },
    "6281233152058": {
      "registeredAt": 1770715286802,
      "expiredAt": 1771320086802,
      "type": "trial"
    },
    "6281330295035": {
      "registeredAt": 1770715457667,
      "expiredAt": 1771320257667,
      "type": "trial"
    },
    "584165592342": {
      "registeredAt": 1770715785548,
      "expiredAt": 1771320585548,
      "type": "trial"
    },
    "62895401593426": {
      "registeredAt": 1770719214621,
      "expiredAt": 1771324014621,
      "type": "trial"
    },
    "62882003172022": {
      "registeredAt": 1770723050427,
      "expiredAt": 1771327850427,
      "type": "trial"
    },
    "6285600532493": {
      "registeredAt": 1770725899146,
      "expiredAt": 1771330699146,
      "type": "trial"
    },
    "6283173192856": {
      "registeredAt": 1770725993116,
      "expiredAt": 1771330793116,
      "type": "trial"
    },
    "17423333289": {
      "registeredAt": 1770726439438,
      "expiredAt": 1771331239438,
      "type": "trial"
    },
    "639752614292": {
      "registeredAt": 1770726593096,
      "expiredAt": 1771331393096,
      "type": "trial"
    },
    "6282326915936": {
      "registeredAt": 1770726911002,
      "expiredAt": 1771331711002,
      "type": "trial"
    },
    "6287880006557": {
      "registeredAt": 1770727040087,
      "expiredAt": 1771331840087,
      "type": "trial"
    },
    "6285168822192": {
      "registeredAt": 1770727652472,
      "expiredAt": 1771332452472,
      "type": "trial"
    },
    "6285876123777": {
      "registeredAt": 1770727970312,
      "expiredAt": 1771332770312,
      "type": "trial"
    },
    "6282229259122": {
      "registeredAt": 1770728091562,
      "expiredAt": 1771332891562,
      "type": "trial"
    },
    "6288245094970": {
      "registeredAt": 1770728342657,
      "expiredAt": 1771333142657,
      "type": "trial"
    },
    "6288245084970": {
      "registeredAt": 1770729372029,
      "expiredAt": 1771334172029,
      "type": "trial"
    },
    "6289612318730": {
      "registeredAt": 1770729549387,
      "expiredAt": 1771334349387,
      "type": "trial"
    },
    "601137643531": {
      "registeredAt": 1770730088086,
      "expiredAt": 1771334888086,
      "type": "trial"
    },
    "628980237308": {
      "registeredAt": 1770730284948,
      "expiredAt": 1771335084948,
      "type": "trial"
    },
    "083136846079": {
      "registeredAt": 1770731961230,
      "expiredAt": 1771336761230,
      "type": "trial"
    },
    "6288905650102": {
      "registeredAt": 1770732437993,
      "expiredAt": 1771337237993,
      "type": "trial"
    },
    "6288245296865": {
      "registeredAt": 1770732742768,
      "expiredAt": 1771337542768,
      "type": "trial"
    },
    "6285122526817": {
      "registeredAt": 1770732873672,
      "expiredAt": 1771337673672,
      "type": "trial"
    },
    "6287797057824": {
      "registeredAt": 1770734190666,
      "expiredAt": 1771338990666,
      "type": "trial"
    },
    "6285167351763": {
      "registeredAt": 1770734978289,
      "expiredAt": 1771339778289,
      "type": "trial"
    },
    "60178139636": {
      "registeredAt": 1770736377133,
      "expiredAt": 1771341177133,
      "type": "trial"
    },
    "62088707099859": {
      "registeredAt": 1770742790820,
      "expiredAt": 1771347590820,
      "type": "trial"
    },
    "6283171721049": {
      "registeredAt": 1770744568486,
      "expiredAt": 1771349368486,
      "type": "trial"
    },
    "639752703632": {
      "registeredAt": 1770747658552,
      "expiredAt": 1771352458552,
      "type": "trial"
    },
    "639752703623": {
      "registeredAt": 1770747731724,
      "expiredAt": 1771352531724,
      "type": "trial"
    },
    "62895326322746": {
      "registeredAt": 1770748471239,
      "expiredAt": 1771353271239,
      "type": "trial"
    },
    "6282199271286": {
      "registeredAt": 1770763884792,
      "expiredAt": 1771368684792,
      "type": "trial"
    },
    "584265853738": {
      "registeredAt": 1770763945410,
      "expiredAt": 1771368745410,
      "type": "trial"
    },
    "60134114759": {
      "registeredAt": 1770769264400,
      "expiredAt": 1771374064400,
      "type": "trial"
    },
    "6285187216119": {
      "registeredAt": 1770772911053,
      "expiredAt": 1771377711053,
      "type": "trial"
    },
    "623124892736": {
      "registeredAt": 1770776059384,
      "expiredAt": 1771380859384,
      "type": "trial"
    },
    "6285837302937": {
      "registeredAt": 1770779147282,
      "expiredAt": 1771383947282,
      "type": "trial"
    },
    "50933106290": {
      "registeredAt": 1770779953177,
      "expiredAt": 1771384753177,
      "type": "trial"
    },
    "584241740075": {
      "registeredAt": 1770788240886,
      "expiredAt": 1771393040886,
      "type": "trial"
    },
    "6283157543605": {
      "registeredAt": 1770788628610,
      "expiredAt": 1771393428610,
      "type": "trial"
    },
    "79647739225": {
      "registeredAt": 1770789124340,
      "expiredAt": 1771393924340,
      "type": "trial"
    },
    "6281318538154": {
      "registeredAt": 1770789622265,
      "expiredAt": 1771394422265,
      "type": "trial"
    },
    "918370902004": {
      "registeredAt": 1770792657918,
      "expiredAt": 1771397457918,
      "type": "trial"
    },
    "6288269647211": {
      "registeredAt": 1770793651070,
      "expiredAt": 1771398451070,
      "type": "trial"
    },
    "6288806395649": {
      "registeredAt": 1770795372045,
      "expiredAt": 1771400172045,
      "type": "trial"
    },
    "6285124631039": {
      "registeredAt": 1770795996534,
      "expiredAt": 1771400796534,
      "type": "trial"
    },
    "6283141890863": {
      "registeredAt": 1770796051551,
      "expiredAt": 1771400851551,
      "type": "trial"
    },
    "6283178013729": {
      "registeredAt": 1770797500986,
      "expiredAt": 1771402300986,
      "type": "trial"
    },
    "6287775851039": {
      "registeredAt": 1770797816767,
      "expiredAt": 1771402616767,
      "type": "trial"
    },
    "6281316744921": {
      "registeredAt": 1770798038628,
      "expiredAt": 1771402838628,
      "type": "trial"
    },
    "6281532451980": {
      "registeredAt": 1770799239917,
      "expiredAt": 1771404039917,
      "type": "trial"
    },
    "6282148836034": {
      "registeredAt": 1770799727694,
      "expiredAt": 1771404527694,
      "type": "trial"
    },
    "62881038142824": {
      "registeredAt": 1770801148893,
      "expiredAt": 1771405948893,
      "type": "trial"
    },
    "639754853459": {
      "registeredAt": 1770802142063,
      "expiredAt": 1771406942063,
      "type": "trial"
    },
    "6283848308994": {
      "registeredAt": 1770802495842,
      "expiredAt": 1771407295842,
      "type": "trial"
    },
    "6282379118433": {
      "registeredAt": 1770802621310,
      "expiredAt": 1771407421310,
      "type": "trial"
    },
    "93775432502": {
      "registeredAt": 1770804292470,
      "expiredAt": 1771409092470,
      "type": "trial"
    },
    "6285839213492": {
      "registeredAt": 1770806027362,
      "expiredAt": 1771410827362,
      "type": "trial"
    },
    "6285789717403": {
      "registeredAt": 1770806489054,
      "expiredAt": 1771411289054,
      "type": "trial"
    },
    "6282172545629": {
      "registeredAt": 1770806825022,
      "expiredAt": 1771411625022,
      "type": "trial"
    },
    "6285849152267": {
      "registeredAt": 1770809718766,
      "expiredAt": 1771414518766,
      "type": "trial"
    },
    "601116765909": {
      "registeredAt": 1770810420493,
      "expiredAt": 1771415220493,
      "type": "trial"
    },
    "6285373520654": {
      "registeredAt": 1770810470804,
      "expiredAt": 1771415270804,
      "type": "trial"
    },
    "6289681586047": {
      "registeredAt": 1770810814850,
      "expiredAt": 1771415614850,
      "type": "trial"
    },
    "6285890294003": {
      "registeredAt": 1770811611518,
      "expiredAt": 1771416411518,
      "type": "trial"
    },
    "6285824743510": {
      "registeredAt": 1770812740324,
      "expiredAt": 1771417540324,
      "type": "trial"
    },
    "6283111162369": {
      "registeredAt": 1770812889457,
      "expiredAt": 1771417689457,
      "type": "trial"
    },
    "6285135322033": {
      "registeredAt": 1770813633577,
      "expiredAt": 1771418433577,
      "type": "trial"
    },
    "6285755121697": {
      "type": "premium",
      "expiredAt": 1773406558573
    },
    "6282153921775": {
      "registeredAt": 1770816610115,
      "expiredAt": 1771421410115,
      "type": "trial"
    },
    "6283132515091": {
      "registeredAt": 1770817302767,
      "expiredAt": 1771422102767,
      "type": "trial"
    },
    "6282326528169": {
      "registeredAt": 1770817744757,
      "expiredAt": 1771422544757,
      "type": "trial"
    },
    "6289518615315": {
      "registeredAt": 1770818378535,
      "expiredAt": 1771423178535,
      "type": "trial"
    },
    "6283139417421": {
      "registeredAt": 1770819550817,
      "expiredAt": 1771424350817,
      "type": "trial"
    },
    "6287858345347": {
      "registeredAt": 1770822201743,
      "expiredAt": 1771427001743,
      "type": "trial"
    },
    "6283151255026": {
      "registeredAt": 1770823585539,
      "expiredAt": 1771428385539,
      "type": "trial"
    },
    "62895805043355": {
      "registeredAt": 1770823652085,
      "expiredAt": 1771428452085,
      "type": "trial"
    },
    "6285147718665": {
      "registeredAt": 1770832564773,
      "expiredAt": 1771437364773,
      "type": "trial"
    },
    "6289673556683": {
      "registeredAt": 1770838218059,
      "expiredAt": 1771443018059,
      "type": "trial"
    },
    "6281255816359": {
      "registeredAt": 1770838288818,
      "expiredAt": 1771443088818,
      "type": "trial"
    },
    "6285274240049": {
      "registeredAt": 1770847957008,
      "expiredAt": 1771452757008,
      "type": "trial"
    },
    "628131362489": {
      "registeredAt": 1770849412150,
      "expiredAt": 1771454212150,
      "type": "trial"
    },
    "6288740370189": {
      "registeredAt": 1770856529037,
      "expiredAt": 1771461329037,
      "type": "trial"
    },
    "6285122529224": {
      "registeredAt": 1770857225329,
      "expiredAt": 1771462025329,
      "type": "trial"
    },
    "6285545188311": {
      "registeredAt": 1770858297605,
      "expiredAt": 1771463097605,
      "type": "trial"
    },
    "628811407292": {
      "registeredAt": 1770860344775,
      "expiredAt": 1771465144775,
      "type": "trial"
    },
    "6281927980933": {
      "registeredAt": 1770866379179,
      "expiredAt": 1771471179179,
      "type": "trial"
    },
    "6283876228787": {
      "registeredAt": 1770867080159,
      "expiredAt": 1771471880159,
      "type": "trial"
    },
    "628817422796": {
      "registeredAt": 1770871991248,
      "expiredAt": 1771476791248,
      "type": "trial"
    },
    "6285602700647": {
      "registeredAt": 1770875352294,
      "expiredAt": 1771480152294,
      "type": "trial"
    },
    "6285805144810": {
      "registeredAt": 1770876237048,
      "expiredAt": 1771481037048,
      "type": "trial"
    },
    "6285869323522": {
      "registeredAt": 1770878143788,
      "expiredAt": 1771482943788,
      "type": "trial"
    },
    "6283138237808": {
      "registeredAt": 1770879549462,
      "expiredAt": 1771484349462,
      "type": "trial"
    },
    "6281549031125": {
      "registeredAt": 1770880210660,
      "expiredAt": 1771485010660,
      "type": "trial"
    },
    "62881036725404": {
      "registeredAt": 1770883571494,
      "expiredAt": 1771488371494,
      "type": "trial"
    },
    "6287768275809": {
      "registeredAt": 1770884196578,
      "expiredAt": 1771488996578,
      "type": "trial"
    },
    "6285606591009": {
      "registeredAt": 1770886514431,
      "expiredAt": 1771491314431,
      "type": "trial"
    },
    "6285743429081": {
      "registeredAt": 1770886833364,
      "expiredAt": 1771491633364,
      "type": "trial"
    },
    "6289696303235": {
      "registeredAt": 1770887056526,
      "expiredAt": 1771491856526,
      "type": "trial"
    },
    "6282116296269": {
      "registeredAt": 1770890298035,
      "expiredAt": 1771495098035,
      "type": "trial"
    },
    "628888009688": {
      "registeredAt": 1770891946155,
      "expiredAt": 1771496746155,
      "type": "trial"
    },
    "6283856016034": {
      "registeredAt": 1770892563162,
      "expiredAt": 1771497363162,
      "type": "trial"
    },
    "584263741417": {
      "registeredAt": 1770895674881,
      "expiredAt": 1771500474881,
      "type": "trial"
    },
    "6283122171450": {
      "registeredAt": 1770896901493,
      "expiredAt": 1771501701493,
      "type": "trial"
    },
    "6285624505786": {
      "registeredAt": 1770897842973,
      "expiredAt": 1771502642973,
      "type": "trial"
    },
    "6283136192672": {
      "registeredAt": 1770899467426,
      "expiredAt": 1771504267426,
      "type": "trial"
    },
    "6288226885067": {
      "registeredAt": 1770900366737,
      "expiredAt": 1771505166737,
      "type": "trial"
    },
    "6285148440927": {
      "registeredAt": 1770902069208,
      "expiredAt": 1771506869208,
      "type": "trial"
    },
    "6283181498767": {
      "registeredAt": 1770902412254,
      "expiredAt": 1771507212254,
      "type": "trial"
    },
    "62895359682921": {
      "registeredAt": 1770902964727,
      "expiredAt": 1771507764727,
      "type": "trial"
    },
    "6285769454164": {
      "registeredAt": 1770903832298,
      "expiredAt": 1771508632298,
      "type": "trial"
    },
    "6287721854974": {
      "registeredAt": 1770903962179,
      "expiredAt": 1771508762179,
      "type": "trial"
    },
    "6282246040039": {
      "registeredAt": 1770904505040,
      "expiredAt": 1771509305040,
      "type": "trial"
    },
    "6288905442436": {
      "registeredAt": 1770904753670,
      "expiredAt": 1771509553670,
      "type": "trial"
    },
    "895370017643": {
      "registeredAt": 1770905678176,
      "expiredAt": 1771510478176,
      "type": "trial"
    },
    "0895370017643": {
      "registeredAt": 1770905834353,
      "expiredAt": 1771510634353,
      "type": "trial"
    },
    "6287819156915": {
      "registeredAt": 1770906004060,
      "expiredAt": 1771510804060,
      "type": "trial"
    },
    "62895370017643": {
      "registeredAt": 1770906057045,
      "expiredAt": 1771510857045,
      "type": "trial"
    },
    "6285695464305": {
      "registeredAt": 1770906922005,
      "expiredAt": 1771511722005,
      "type": "trial"
    },
    "6282227073158": {
      "registeredAt": 1770907282553,
      "expiredAt": 1771512082553,
      "type": "trial"
    },
    "6285757178914": {
      "registeredAt": 1770907867028,
      "expiredAt": 1771512667028,
      "type": "trial"
    },
    "6288279241138": {
      "registeredAt": 1770907927583,
      "expiredAt": 1771512727583,
      "type": "trial"
    },
    "6283134441784": {
      "registeredAt": 1770908131253,
      "expiredAt": 1771512931253,
      "type": "trial"
    },
    "6285647510389": {
      "registeredAt": 1770909475699,
      "expiredAt": 1771514275699,
      "type": "trial"
    },
    "6289528146823": {
      "registeredAt": 1770910379466,
      "expiredAt": 1771515179466,
      "type": "trial"
    },
    "60199494091": {
      "registeredAt": 1770910501179,
      "expiredAt": 1771515301179,
      "type": "trial"
    },
    "584262449768": {
      "registeredAt": 1770910847276,
      "expiredAt": 1771515647276,
      "type": "trial"
    },
    "6285776789031": {
      "registeredAt": 1770911034904,
      "expiredAt": 1771515834904,
      "type": "trial"
    },
    "6285881682291": {
      "registeredAt": 1770912063487,
      "expiredAt": 1771516863487,
      "type": "trial"
    },
    "62895370018643": {
      "registeredAt": 1770912190598,
      "expiredAt": 1771516990598,
      "type": "trial"
    },
    "6283172680189": {
      "registeredAt": 1770912616858,
      "expiredAt": 1771517416858,
      "type": "trial"
    },
    "6283183262714": {
      "registeredAt": 1770912758916,
      "expiredAt": 1771517558916,
      "type": "trial"
    },
    "628136791139": {
      "type": "premium",
      "expiredAt": 1773508489051
    },
    "6283892460420": {
      "registeredAt": 1770921947713,
      "expiredAt": 1771526747713,
      "type": "trial"
    },
    "917278557347": {
      "registeredAt": 1770925548907,
      "expiredAt": 1771530348907,
      "type": "trial"
    },
    "6285750289048": {
      "registeredAt": 1770935605232,
      "expiredAt": 1771540405232,
      "type": "trial"
    },
    "625750289048": {
      "registeredAt": 1770935865635,
      "expiredAt": 1771540665635,
      "type": "trial"
    },
    "6283380274": {
      "registeredAt": 1770941810678,
      "expiredAt": 1771546610678,
      "type": "trial"
    },
    "6288906235110": {
      "registeredAt": 1770943530208,
      "expiredAt": 1771548330208,
      "type": "trial"
    },
    "6283187658157": {
      "registeredAt": 1770945465029,
      "expiredAt": 1771550265029,
      "type": "trial"
    },
    "6281318967969": {
      "registeredAt": 1770945530185,
      "expiredAt": 1771550330185,
      "type": "trial"
    },
    "6283838714930": {
      "registeredAt": 1770948905343,
      "expiredAt": 1771553705343,
      "type": "trial"
    },
    "6283171031039": {
      "registeredAt": 1770949957940,
      "expiredAt": 1771554757940,
      "type": "trial"
    },
    "6288704739139": {
      "registeredAt": 1770951484459,
      "expiredAt": 1771556284459,
      "type": "trial"
    },
    "639687231642": {
      "registeredAt": 1770952736038,
      "expiredAt": 1771557536038,
      "type": "trial"
    },
    "6283848354660": {
      "registeredAt": 1770953332494,
      "expiredAt": 1771558132494,
      "type": "trial"
    },
    "584262912572": {
      "registeredAt": 1770956256319,
      "expiredAt": 1771561056319,
      "type": "trial"
    },
    "6282142695995": {
      "registeredAt": 1770957296688,
      "expiredAt": 1771562096688,
      "type": "trial"
    },
    "6283848532470": {
      "registeredAt": 1770957736443,
      "expiredAt": 1771562536443,
      "type": "trial"
    },
    "6285951486231": {
      "registeredAt": 1770960923016,
      "expiredAt": 1771565723016,
      "type": "trial"
    },
    "6285148343042": {
      "registeredAt": 1770961197522,
      "expiredAt": 1771565997522,
      "type": "trial"
    },
    "628388007915": {
      "registeredAt": 1770962378688,
      "expiredAt": 1771567178688,
      "type": "trial"
    },
    "6283839262355": {
      "registeredAt": 1770963024876,
      "expiredAt": 1771567824876,
      "type": "trial"
    },
    "6285849179467": {
      "registeredAt": 1770969043548,
      "expiredAt": 1771573843548,
      "type": "trial"
    },
    "6289654743520": {
      "registeredAt": 1770969594388,
      "expiredAt": 1771574394388,
      "type": "trial"
    },
    "6283856625145": {
      "registeredAt": 1770970121936,
      "expiredAt": 1771574921936,
      "type": "trial"
    },
    "62895326079465": {
      "registeredAt": 1770970237470,
      "expiredAt": 1771575037470,
      "type": "trial"
    },
    "6285213582421": {
      "registeredAt": 1770970514873,
      "expiredAt": 1771575314873,
      "type": "trial"
    },
    "639754302453": {
      "registeredAt": 1770972513384,
      "expiredAt": 1771577313384,
      "type": "trial"
    },
    "6282143979383": {
      "registeredAt": 1770973330419,
      "expiredAt": 1771578130419,
      "type": "trial"
    },
    "6285814810931": {
      "registeredAt": 1770976063059,
      "expiredAt": 1771580863059,
      "type": "trial"
    },
    "84903938840": {
      "registeredAt": 1770976392635,
      "expiredAt": 1771581192635,
      "type": "trial"
    },
    "6285187724672": {
      "registeredAt": 1770978231245,
      "expiredAt": 1771583031245,
      "type": "trial"
    },
    "6285815144915": {
      "registeredAt": 1770978951284,
      "expiredAt": 1771583751284,
      "type": "trial"
    },
    "6283190650758": {
      "registeredAt": 1770980209349,
      "expiredAt": 1771585009349,
      "type": "trial"
    },
    "6282295845369": {
      "registeredAt": 1770983286214,
      "expiredAt": 1771588086214,
      "type": "trial"
    },
    "6283826551099": {
      "registeredAt": 1770983983757,
      "expiredAt": 1771588783757,
      "type": "trial"
    },
    "6283852406404": {
      "registeredAt": 1770984085164,
      "expiredAt": 1771588885164,
      "type": "trial"
    },
    "60196160149": {
      "registeredAt": 1770984116739,
      "expiredAt": 1771588916739,
      "type": "trial"
    },
    "6383852406404": {
      "registeredAt": 1770984184723,
      "expiredAt": 1771588984723,
      "type": "trial"
    },
    "683852406404": {
      "registeredAt": 1770984348447,
      "expiredAt": 1771589148447,
      "type": "trial"
    },
    "62083852406404": {
      "registeredAt": 1770984394155,
      "expiredAt": 1771589194155,
      "type": "trial"
    },
    "3197010505641": {
      "registeredAt": 1770985993367,
      "expiredAt": 1771590793367,
      "type": "trial"
    },
    "6282343157601": {
      "registeredAt": 1770986564504,
      "expiredAt": 1771591364504,
      "type": "trial"
    },
    "6285776187433": {
      "registeredAt": 1770991341471,
      "expiredAt": 1771596141471,
      "type": "trial"
    },
    "6285773329770": {
      "registeredAt": 1770991420737,
      "expiredAt": 1771596220737,
      "type": "trial"
    },
    "6282126019797": {
      "registeredAt": 1770992165743,
      "expiredAt": 1771596965743,
      "type": "trial"
    },
    "6281319594467": {
      "registeredAt": 1770992452457,
      "expiredAt": 1771597252457,
      "type": "trial"
    },
    "6288296597132": {
      "registeredAt": 1770992999341,
      "expiredAt": 1771597799341,
      "type": "trial"
    },
    "62895406525734": {
      "registeredAt": 1770993053963,
      "expiredAt": 1771597853963,
      "type": "trial"
    },
    "6287817351865": {
      "registeredAt": 1770993165878,
      "expiredAt": 1771597965878,
      "type": "trial"
    },
    "6285199554420": {
      "registeredAt": 1770993439706,
      "expiredAt": 1771598239706,
      "type": "trial"
    },
    "6285713909548": {
      "registeredAt": 1770993776734,
      "expiredAt": 1771598576734,
      "type": "trial"
    },
    "6288994164176": {
      "registeredAt": 1770994087946,
      "expiredAt": 1771598887946,
      "type": "trial"
    },
    "6285187153237": {
      "registeredAt": 1770994251541,
      "expiredAt": 1771599051541,
      "type": "trial"
    },
    "6283168171024": {
      "registeredAt": 1770994914861,
      "expiredAt": 1771599714861,
      "type": "trial"
    },
    "6285156258107": {
      "registeredAt": 1770995318053,
      "expiredAt": 1771600118053,
      "type": "trial"
    },
    "6285182973247": {
      "registeredAt": 1770995372939,
      "expiredAt": 1771600172939,
      "type": "trial"
    },
    "60197625200": {
      "registeredAt": 1770998942344,
      "expiredAt": 1771603742344,
      "type": "trial"
    },
    "584162504395": {
      "registeredAt": 1771001395166,
      "expiredAt": 1771606195166,
      "type": "trial"
    },
    "6281264182352": {
      "registeredAt": 1771007945419,
      "expiredAt": 1771612745419,
      "type": "trial"
    },
    "62895620781060": {
      "registeredAt": 1771008972576,
      "expiredAt": 1771613772576,
      "type": "trial"
    },
    "6283857330960": {
      "registeredAt": 1771009521637,
      "expiredAt": 1771614321637,
      "type": "trial"
    },
    "50940576270": {
      "registeredAt": 1771009555755,
      "expiredAt": 1771614355755,
      "type": "trial"
    },
    "6289504575653": {
      "registeredAt": 1771012332121,
      "expiredAt": 1771617132121,
      "type": "trial"
    },
    "6285815183635": {
      "registeredAt": 1771014511939,
      "expiredAt": 1771619311939,
      "type": "trial"
    },
    "6289525821712": {
      "registeredAt": 1771017144954,
      "expiredAt": 1771621944954,
      "type": "trial"
    },
    "6281393171563": {
      "registeredAt": 1771018680449,
      "expiredAt": 1771623480449,
      "type": "trial"
    },
    "6281341095770": {
      "registeredAt": 1771023647384,
      "expiredAt": 1771628447384,
      "type": "trial"
    },
    "6282279915224": {
      "registeredAt": 1771024425113,
      "expiredAt": 1771629225113,
      "type": "trial"
    },
    "6285835247216": {
      "registeredAt": 1771024864025,
      "expiredAt": 1771629664025,
      "type": "trial"
    },
    "9779824799499": {
      "registeredAt": 1771024977299,
      "expiredAt": 1771629777299,
      "type": "trial"
    },
    "6283178505797": {
      "registeredAt": 1771025465290,
      "expiredAt": 1771630265290,
      "type": "trial"
    },
    "59175209059": {
      "registeredAt": 1771026491942,
      "expiredAt": 1771631291942,
      "type": "trial"
    },
    "62895365308337": {
      "registeredAt": 1771030145713,
      "expiredAt": 1771634945713,
      "type": "trial"
    },
    "6285664992570": {
      "registeredAt": 1771031393928,
      "expiredAt": 1771636193928,
      "type": "trial"
    },
    "27687613434": {
      "registeredAt": 1771032855889,
      "expiredAt": 1771637655889,
      "type": "trial"
    },
    "6283186636882": {
      "registeredAt": 1771038514265,
      "expiredAt": 1771643314265,
      "type": "trial"
    },
    "6285847751873": {
      "registeredAt": 1771039318527,
      "expiredAt": 1771644118527,
      "type": "trial"
    },
    "6283135838658": {
      "registeredAt": 1771039555644,
      "expiredAt": 1771644355644,
      "type": "trial"
    },
    "628895341009": {
      "registeredAt": 1771040416074,
      "expiredAt": 1771645216074,
      "type": "trial"
    },
    "6282289355072": {
      "registeredAt": 1771040733628,
      "expiredAt": 1771645533628,
      "type": "trial"
    },
    "6285719439584": {
      "registeredAt": 1771041154536,
      "expiredAt": 1771645954536,
      "type": "trial"
    },
    "6283187786109": {
      "registeredAt": 1771041317696,
      "expiredAt": 1771646117696,
      "type": "trial"
    },
    "996770303195": {
      "registeredAt": 1771041583951,
      "expiredAt": 1771646383951,
      "type": "trial"
    },
    "6282281496707": {
      "registeredAt": 1771046990696,
      "expiredAt": 1771651790696,
      "type": "trial"
    },
    "6288226829849": {
      "registeredAt": 1771049220469,
      "expiredAt": 1771654020469,
      "type": "trial"
    },
    "6285194541704": {
      "registeredAt": 1771049607850,
      "expiredAt": 1771654407850,
      "type": "trial"
    },
    "6287728678521": {
      "registeredAt": 1771049700675,
      "expiredAt": 1771654500675,
      "type": "trial"
    },
    "85809340572": {
      "registeredAt": 1771050556255,
      "expiredAt": 1771655356255,
      "type": "trial"
    },
    "085809340573": {
      "registeredAt": 1771050643479,
      "expiredAt": 1771655443479,
      "type": "trial"
    },
    "6285809340572": {
      "registeredAt": 1771050727546,
      "expiredAt": 1771655527546,
      "type": "trial"
    },
    "62882001355651": {
      "registeredAt": 1771050982422,
      "expiredAt": 1771655782422,
      "type": "trial"
    },
    "6281343054165": {
      "registeredAt": 1771052033222,
      "expiredAt": 1771656833222,
      "type": "trial"
    },
    "62895329565942": {
      "registeredAt": 1771053988185,
      "expiredAt": 1771658788185,
      "type": "trial"
    },
    "6285725284682": {
      "registeredAt": 1771055540369,
      "expiredAt": 1771660340369,
      "type": "trial"
    },
    "6289682381342": {
      "registeredAt": 1771055994817,
      "expiredAt": 1771660794817,
      "type": "trial"
    },
    "6285755279244": {
      "registeredAt": 1771056321508,
      "expiredAt": 1771661121508,
      "type": "trial"
    },
    "6289525742309": {
      "registeredAt": 1771056495440,
      "expiredAt": 1771661295440,
      "type": "trial"
    },
    "6285755290124": {
      "registeredAt": 1771057152281,
      "expiredAt": 1771661952281,
      "type": "trial"
    },
    "6282175637907": {
      "registeredAt": 1771057994451,
      "expiredAt": 1771662794451,
      "type": "trial"
    },
    "6281356556131": {
      "registeredAt": 1771058221647,
      "expiredAt": 1771663021647,
      "type": "trial"
    },
    "6285763604603": {
      "registeredAt": 1771058758759,
      "expiredAt": 1771663558759,
      "type": "trial"
    },
    "6285720660100": {
      "registeredAt": 1771058871455,
      "expiredAt": 1771663671455,
      "type": "trial"
    },
    "6287885378596": {
      "registeredAt": 1771059270351,
      "expiredAt": 1771664070351,
      "type": "trial"
    }
  }
}